scryptomath.py
scryptomath-0.0.6.dist-info/LICENSE
scryptomath-0.0.6.dist-info/METADATA
scryptomath-0.0.6.dist-info/WHEEL
scryptomath-0.0.6.dist-info/top_level.txt
scryptomath-0.0.6.dist-info/RECORD
