Metadata-Version: 2.1
Name: scryptomath
Version: 0.0.6
Summary: Math library to support writing Python tests for Scrypto blueprints
Author-email: Ociswap <dev@ociswap.com>
License: MIT License
Project-URL: Homepage, https://github.com/ociswap/scrypto-math
Keywords: scrypto,math
Classifier: License :: OSI Approved :: MIT License
Classifier: Programming Language :: Python
Classifier: Programming Language :: Python :: 3
Requires-Python: >=3.9
License-File: LICENSE
